fastforward/__init__.py
fastforward/cinder.py
fastforward/cli.py
fastforward/cliutil.py
fastforward/environment.py
fastforward/glance.py
fastforward/haproxy.py
fastforward/horizon.py
fastforward/keystone.py
fastforward/manila.py
fastforward/manila_share.py
fastforward/mysql.py
fastforward/neutron.py
fastforward/neutron_agent.py
fastforward/new.py
fastforward/nova.py
fastforward/nova_compute.py
fastforward/rabbitmq.py
fastforward/swift.py
fastforward/swift_storage.py
fastforward-0.0.10.dist-info/DESCRIPTION.rst
fastforward-0.0.10.dist-info/METADATA
fastforward-0.0.10.dist-info/RECORD
fastforward-0.0.10.dist-info/WHEEL
fastforward-0.0.10.dist-info/entry_points.txt
fastforward-0.0.10.dist-info/metadata.json
fastforward-0.0.10.dist-info/top_level.txt
