Metadata-Version: 2.0
Name: fastforward
Version: 0.0.10
Summary: FastForward is a DevOps automate platform
Home-page: https://github.com/nofdev/fastforward
Author: nofdev
Author-email: jiasir@icloud.com
License: MIT
Platform: UNKNOWN
Requires-Dist: playback (==0.3.8)
